nspyre_drivers/__init__.py
nspyre_drivers/acton/sp2150i/sp2150i.py
nspyre_drivers/acton/sp2150i/sp2150i_gui.py
nspyre_drivers/agiltron/__init__.py
nspyre_drivers/agiltron/ffsw/__init__.py
nspyre_drivers/agiltron/ffsw/ffsw.py
nspyre_drivers/agiltron/ffsw/ffsw_gui.py
nspyre_drivers/arduino/__init__.py
nspyre_drivers/arduino/arduino_gpio/README.md
nspyre_drivers/arduino/arduino_gpio/__init__.py
nspyre_drivers/arduino/arduino_gpio/arduino_gpio.py
nspyre_drivers/arduino/arduino_gpio/arduino_gpio_gui.py
nspyre_drivers/arduino/arduino_gpio/pin_server/pin_server.ino
nspyre_drivers/beaglebone/__init__.py
nspyre_drivers/beaglebone/beaglebone_gpio/__init__.py
nspyre_drivers/beaglebone/beaglebone_gpio/beaglebone_gpio.py
nspyre_drivers/beaglebone/beaglebone_gpio/beaglebone_gpio_gui.py
nspyre_drivers/beaglebone/beaglebone_gpio/beaglebone_server/README.txt
nspyre_drivers/beaglebone/beaglebone_gpio/beaglebone_server/gpio_flask_server.py
nspyre_drivers/beaglebone/beaglebone_gpio/beaglebone_server/gpio_flask_server.service
nspyre_drivers/cobolt/__init__.py
nspyre_drivers/cobolt/cobolt_gui.py
nspyre_drivers/cv2_cam/__init__.py
nspyre_drivers/cv2_cam/cv2_cam_gui.py
nspyre_drivers/dli_pdu/__init__.py
nspyre_drivers/dli_pdu/dli_pdu.py
nspyre_drivers/dlnsec/__init__.py
nspyre_drivers/dlnsec/dlnsec.py
nspyre_drivers/dlnsec/dlnsec_gui.py
nspyre_drivers/luminox/__init__.py
nspyre_drivers/luminox/luminox.py
nspyre_drivers/ni/__init__.py
nspyre_drivers/ni/daq.py
nspyre_drivers/ni/ni_motion_controller.py
nspyre_drivers/oceanoptics/__init__.py
nspyre_drivers/oceanoptics/hr2000es/__init__.py
nspyre_drivers/oceanoptics/hr2000es/hr2000es.py
nspyre_drivers/oceanoptics/hr2000es/hr2000es_gui.py
nspyre_drivers/oceanoptics/hr2000es/oceandirect/PythonOceanDirect_User_Manual.rtf
nspyre_drivers/oceanoptics/hr2000es/oceandirect/sample_pack/C/CExampleForOceanDirect.c
nspyre_drivers/oceanoptics/hr2000es/oceandirect/sample_pack/CPlusPlus/CPlusPlusExampeForOceanDirect.cpp
nspyre_drivers-0.1.6.dist-info/LICENSE
nspyre_drivers-0.1.6.dist-info/WHEEL
nspyre_drivers-0.1.6.dist-info/METADATA
nspyre_drivers-0.1.6.dist-info/RECORD
