Metadata-Version: 2.1
Name: nspyre-drivers
Version: 0.1.6
Summary: A set of Python drivers for lab instrumentation.
Author: Jacob Feder
Author-email: jacobsfeder@gmail.com
Maintainer: Jacob Feder
Maintainer-email: jacobsfeder@gmail.com
Requires-Python: >=3.7,<4.0
Classifier: Programming Language :: Python :: 3
Classifier: Programming Language :: Python :: 3.10
Classifier: Programming Language :: Python :: 3.7
Classifier: Programming Language :: Python :: 3.8
Classifier: Programming Language :: Python :: 3.9
Provides-Extra: beaglebone
Provides-Extra: dli_pdu
Provides-Extra: nidaq
Provides-Extra: oceanoptics
Provides-Extra: ximea
Provides-Extra: zaber
Requires-Dist: beautifulsoup4; extra == "dli_pdu"
Requires-Dist: dlipower; extra == "dli_pdu"
Requires-Dist: nidaqmx; extra == "nidaq"
Requires-Dist: numpy
Requires-Dist: pyserial
Requires-Dist: pyusb
Requires-Dist: pyvisa
Requires-Dist: pyvisa-py
Requires-Dist: requests; extra == "beaglebone"
Requires-Dist: seabreeze; extra == "oceanoptics"
Requires-Dist: ximea-py; extra == "ximea"
Requires-Dist: zaber-motion; extra == "zaber"
